tmandate/__init__.py
tmandate/client.py
tmandate/formatters.py
tmandate/protocol.py
tmandate/types.py
tmandate-1.0.0.dist-info/METADATA
tmandate-1.0.0.dist-info/WHEEL
tmandate-1.0.0.dist-info/top_level.txt
tmandate-1.0.0.dist-info/RECORD
