Metadata-Version: 2.4
Name: tmandate
Version: 1.0.0
Summary: TMANDATE Python SDK
Author: TMANDATE
Requires-Python: >=3.8
Requires-Dist: requests>=2.31.0
Dynamic: author
Dynamic: requires-dist
Dynamic: requires-python
Dynamic: summary
